{"is_source_file": true, "format": "JavaScript (React JSX)", "description": "React component for displaying a shared journal view, utilizing a Timeline component", "external_files": ["../components/Timeline"], "external_methods": [], "published": ["SharedJournal"], "classes": [], "methods": [{"name": "SharedJournal({ sharedEntries })", "description": "React functional component that renders a shared journal page with a Timeline", "scope": "", "scopeKind": ""}], "calls": ["React", "Timeline"], "search-terms": ["SharedJournal", "React", "Timeline component", "sharedEntries", "public journal"], "state": 2, "file_id": 24, "knowledge_revision": 50, "git_revision": "", "ctags": [{"_type": "tag", "name": "SharedJournal", "path": "/home/kavia/workspace/code-generation/honeymoon-memory-journal-ad3a6afd/honeymoon_journal_frontend/src/pages/SharedJournal.js", "pattern": "/^function SharedJournal({ sharedEntries }) {$/", "language": "JavaScript", "kind": "function", "signature": "({ sharedEntries })"}, {"_type": "tag", "name": "sharedEntries", "path": "/home/kavia/workspace/code-generation/honeymoon-memory-journal-ad3a6afd/honeymoon_journal_frontend/src/pages/SharedJournal.js", "pattern": "/^      <Timeline entries={sharedEntries || []} \\/>$/", "language": "JavaScript", "kind": "field", "scope": "SharedJournal.AnonymousClass2f64459f0101", "scopeKind": "class"}], "hash": "4d3dfa04a0788d74c0402a5b6bbabab3", "format-version": 4, "code-base-name": "honeymoon_journal_frontend", "filename": "honeymoon_journal_frontend/src/pages/SharedJournal.js", "fields": [{"name": "<Timeline entries={sharedEntries || []} \\/>", "scope": "SharedJournal.AnonymousClass2f64459f0101", "scopeKind": "class", "description": "unavailable"}], "revision_history": [{"50": ""}]}